Workbook
Name aporte: Planilha1!$D$19
Name patrimonio: Planilha1!$D$22
Name qtd_anos: Planilha1!$D$20
Name Rendimento_Carteira: Planilha1!$D$15
Name salario: Planilha1!$D$14
Name sugestao_invest: Planilha1!$D$16
Name taxa_mensal: Planilha1!$D$21

Sheet Planilha1
B13: CONFIGURAÇÕES
B14: Salário | D14: 4000
B15: Rendimento Carteira | D15: 0.006
B16: Sugestão de Investimento | D16: =D14*30% -> 1200
B18: INVESTIMENTO MENSAL
B19: Quanto investir por mês? | D19: 400
B20: Por quantos anos? | D20: 10
B21: Taxa de rendimento mensal | D21: 0.01079
B22: Patrimônio acumulado: | D22: =FV(taxa_mensal,qtd_anos*12,aporte*-1) -> 97313.685
B23: Dividendos mensais: | D23: =patrimonio*Rendimento_Carteira -> 583.88211
B25: Cenários | D25: Dividendo
A26: 2 | B26: Quanto em 2 anos? | C26: =FV($D$21,A26*12,D$19*-1) -> 10891.051 | D26: =C26*Rendimento_Carteira -> 65.346306
A27: 5 | B27: Quanto em 5 anos? | C27: =FV($D$21,A27*12,D$19*-1) -> 33510.766 | D27: =C27*Rendimento_Carteira -> 201.06459
A28: 10 | B28: Quanto em 10 anos? | C28: =FV($D$21,A28*12,D$19*-1) -> 97313.685 | D28: =C28*Rendimento_Carteira -> 583.88211
A29: 20 | B29: Quanto em 20 anos? | C29: =FV($D$21,A29*12,D$19*-1) -> 450079.36 | D29: =C29*Rendimento_Carteira -> 2700.4762
A30: 30 | B30: Quanto em 30 anos? | C30: =FV($D$21,A30*12,D$19*-1) -> 1728867.9 | D30: =C30*Rendimento_Carteira -> 10373.207
B33: PERFIL | D33: Conservador
B34: VALOR A SER INVESTIDO POR MÊS | D34: =aporte -> 400
B36: Tipo de FII | C36: Percentual Sugerido | D36: Valores
B37: PAPEL | C37: =VLOOKUP($D$33&"-"&B37,Planilha2!$A:$D,4,FALSE) -> 0.3 | D37: =C37*$D$34 -> 120
B38: TIJOLO | C38: =VLOOKUP($D$33&"-"&B38,Planilha2!$A:$D,4,FALSE) -> 0.5 | D38: =C38*$D$34 -> 200
B39: HÍBRIDOS | C39: =VLOOKUP($D$33&"-"&B39,Planilha2!$A:$D,4,FALSE) -> 0.1 | D39: =C39*$D$34 -> 40
B40: FOFs | C40: =VLOOKUP($D$33&"-"&B40,Planilha2!$A:$D,4,FALSE) -> 0.1 | D40: =C40*$D$34 -> 40
B41: DESENVOLVIMENTO | C41: =VLOOKUP($D$33&"-"&B41,Planilha2!$A:$D,4,FALSE) -> 0 | D41: =C41*$D$34 -> 0
B42: HOTELARIAS | C42: =VLOOKUP($D$33&"-"&B42,Planilha2!$A:$D,4,FALSE) -> 0 | D42: =C42*$D$34 -> 0
D43: =SUM(D37:D42) -> 400

Sheet Planilha2
A2: CHAVE | B2: PERFIL | C2: TIPO DE FII | D2: %
A3: =$B3&"-"&C3 -> Conservador-PAPEL | B3: Conservador | C3: PAPEL | D3: 0.3
A4: =$B4&"-"&C4 -> Conservador-TIJOLO | B4: Conservador | C4: TIJOLO | D4: 0.5 | G4: Moderado-TIJOLO | H4: =VLOOKUP(G4,$A:$D,4,FALSE) -> 0.4
A5: =$B5&"-"&C5 -> Conservador-HÍBRIDOS | B5: Conservador | C5: HÍBRIDOS | D5: 0.1
A6: =$B6&"-"&C6 -> Conservador-FOFs | B6: Conservador | C6: FOFs | D6: 0.1
A7: =$B7&"-"&C7 -> Conservador-DESENVOLVIMENTO | B7: Conservador | C7: DESENVOLVIMENTO | D7: 0
A8: =$B8&"-"&C8 -> Conservador-HOTELARIAS | B8: Conservador | C8: HOTELARIAS | D8: 0
A9: =$B9&"-"&C9 -> Moderado-PAPEL | B9: Moderado | C9: PAPEL | D9: 0.32
A10: =$B10&"-"&C10 -> Moderado-TIJOLO | B10: Moderado | C10: TIJOLO | D10: 0.4
A11: =$B11&"-"&C11 -> Moderado-HÍBRIDOS | B11: Moderado | C11: HÍBRIDOS | D11: 0.08
A12: =$B12&"-"&C12 -> Moderado-FOFs | B12: Moderado | C12: FOFs | D12: 0.1
A13: =$B13&"-"&C13 -> Moderado-DESENVOLVIMENTO | B13: Moderado | C13: DESENVOLVIMENTO | D13: 0.05
A14: =$B14&"-"&C14 -> Moderado-HOTELARIAS | B14: Moderado | C14: HOTELARIAS | D14: 0.05
A15: =$B15&"-"&C15 -> Agressivo-PAPEL | B15: Agressivo | C15: PAPEL | D15: 0.5
A16: =$B16&"-"&C16 -> Agressivo-TIJOLO | B16: Agressivo | C16: TIJOLO | D16: 0.1
... A20: =$B20&"-"&C20 -> Agressivo-HOTELARIAS | B20: Agressivo | C20: HOTELARIAS | D20: 0.1
